{
  "project_info": {
    "project_number": "327427771470",
    "project_id": "mc-5450-challenge3",
    "storage_bucket": "mc-5450-challenge3.firebasestorage.app"
  },
  "client": [
    {
      "client_info": {
        "mobilesdk_app_id": "1:327427771470:android:93695691c8fa9ca247471f",
        "android_client_info": {
          "package_name": "com.example.mastermind_game"
        }
      },
      "oauth_client": [],
      "api_key": [
        {
          "current_key": "AIzaSyBC1FDrQE1yQEzZKvlHgurvaOCGOsREkY8"
        }
      ],
      "services": {
        "appinvite_service": {
          "other_platform_oauth_client": []
        }
      }
    }
  ],
  "configuration_version": "1"
}